ellatu/__init__.py
ellatu/document_editor.py
ellatu/ellatu.py
ellatu/ellatu_bot.py
ellatu/ellatu_db.py
ellatu/image_editing.py
ellatu/mapper.ebnf
ellatu/mapper.py
ellatu/mapper_pipeline.py
ellatu-0.0.20.dist-info/LICENSE
ellatu-0.0.20.dist-info/METADATA
ellatu-0.0.20.dist-info/WHEEL
ellatu-0.0.20.dist-info/top_level.txt
ellatu-0.0.20.dist-info/RECORD
