Metadata-Version: 2.1
Name: ellatu
Version: 0.0.20
Summary: Ellatu is framework for building text based games
Home-page: https://github.com/sixkey/ellatu
License: BSD 3-clause
Platform: UNKNOWN
Classifier: Programming Language :: Python :: 3
Classifier: License :: OSI Approved :: BSD License
Classifier: Operating System :: OS Independent
Requires-Python: >=3.7
License-File: LICENSE
Requires-Dist: discord
Requires-Dist: pillow
Requires-Dist: tatsu
Requires-Dist: numpy
Requires-Dist: pymongo
Requires-Dist: pymongo[srv]
Requires-Dist: pygraphviz
Requires-Dist: python-dotenv
